.DS_Store
dependency_release_tracker/.DS_Store
dependency_release_tracker/__init__.py
dependency_release_tracker/config.py
dependency_release_tracker/main.py
dependency_release_tracker/spm_release_tracker.py
dependency_release_tracker/version.py
dependency_release_tracker/dependency_readers/__init__.py
dependency_release_tracker/dependency_readers/base_reader.py
dependency_release_tracker/dependency_readers/flutter_reader.py
dependency_release_tracker/dependency_readers/swift_reader.py
dependency_release_tracker/display/__init__.py
dependency_release_tracker/display/dependency_display.py
dependency_release_tracker/models/__init__.py
dependency_release_tracker/models/dependency.py
dependency_release_tracker/tests/__init__.py
dependency_release_tracker/tests/test_dependency_display.py
dependency_release_tracker/utils/__init__.py
dependency_release_tracker/utils/dependency_manager_detector.py
dependency_release_tracker/utils/dependency_manager_types.py
dependency_release_tracker/utils/progress_manager.py
dependency_release_tracker-1.0.1.dist-info/LICENSE
dependency_release_tracker-1.0.1.dist-info/METADATA
dependency_release_tracker-1.0.1.dist-info/WHEEL
dependency_release_tracker-1.0.1.dist-info/entry_points.txt
dependency_release_tracker-1.0.1.dist-info/top_level.txt
dependency_release_tracker-1.0.1.dist-info/RECORD
