Metadata-Version: 2.1
Name: dependency_release_tracker
Version: 1.0.1
Summary: An advanced dependency management tool designed to streamline and simplify the update tracking process for various programming environments. This tool extends support beyond Swift to include Flutter, handling both direct and transitive dependencies efficiently. By automating the update checks and changelog retrievals, it ensures developers can easily maintain their projects with the latest library versions, enhancing project stability and feature integration.
Home-page: https://github.com/hugovanderlei/DependencyReleaseTracker
Author: Hugo Vanderlei
Author-email: hugocvcosta@gmail.com
License-File: LICENSE
Requires-Dist: requests
Requires-Dist: rich
Requires-Dist: argparse
Requires-Dist: requests-cache
Requires-Dist: pytz
Requires-Dist: PyYAML
